{
	"parent": "block/block",
	"credit": "Made with Blockbench",
	"textures": {
		"2": "block/birch_planks",
		"particle": "block/birch_planks"
	},
	"elements": [
		{
			"from": [15, 0, 6.5],
			"to": [16, 16, 9],
			"faces": {
				"north": {"uv": [0, 0, 16, 1], "rotation": 90, "texture": "#2"},
				"east": {"uv": [7, 0, 23, 2.5], "rotation": 90, "texture": "#2"},
				"south": {"uv": [15, 0, 31, 1], "rotation": 90, "texture": "#2"},
				"west": {"uv": [6.5, 0, 22.5, 2.5], "rotation": 90, "texture": "#2"},
				"up": {"uv": [15, 6.5, 17.5, 7.5], "rotation": 90, "texture": "#2"},
				"down": {"uv": [15, 7, 17.5, 8], "rotation": 90, "texture": "#2"}
			}
		},
		{
			"from": [0, 0, 6.5],
			"to": [1, 16, 9],
			"faces": {
				"north": {"uv": [15, 0, 31, 1], "rotation": 90, "texture": "#2"},
				"east": {"uv": [7, 0, 23, 2.5], "rotation": 90, "texture": "#2"},
				"south": {"uv": [0, 0, 16, 1], "rotation": 90, "texture": "#2"},
				"west": {"uv": [5, 0, 21, 2.5], "rotation": 90, "texture": "#2"},
				"up": {"uv": [0, 6.5, 2.5, 7.5], "rotation": 90, "texture": "#2"},
				"down": {"uv": [0, 7, 2.5, 8], "rotation": 90, "texture": "#2"}
			}
		},
		{
			"from": [11.75538, 0.5, 7.75],
			"to": [13.75538, 16.25, 8.5],
			"rotation": {"angle": 0, "axis": "y", "origin": [0.98896, 8.26606, 7.74107]},
			"faces": {
				"north": {"uv": [2.5, 0, 18, 1.75], "rotation": 90, "texture": "#2"},
				"east": {"uv": [7, 0.5, 22, 1], "rotation": 90, "texture": "#2"},
				"south": {"uv": [11.75, 0, 27.5, 2], "rotation": 90, "texture": "#2"},
				"west": {"uv": [7, 0.5, 22, 1], "rotation": 90, "texture": "#2"},
				"up": {"uv": [11.75, 7.75, 12.5, 9.75], "rotation": 90, "texture": "#2"},
				"down": {"uv": [11.75, 7.5, 12.5, 9.5], "rotation": 90, "texture": "#2"}
			}
		},
		{
			"from": [0.98975, 12, 6.75],
			"to": [14.98975, 14, 7.75],
			"rotation": {"angle": 0, "axis": "y", "origin": [0.98896, 8.26606, 7.74107]},
			"faces": {
				"north": {"uv": [1, 0, 15, 2], "texture": "#2"},
				"east": {"uv": [9.5, 1.5, 10.5, 3.5], "texture": "#2"},
				"south": {"uv": [0.98438, 2, 14.98438, 4], "texture": "#2"},
				"west": {"uv": [3.5, 4, 4.5, 6], "texture": "#2"},
				"up": {"uv": [0.5, 2, 14.5, 3], "texture": "#2"},
				"down": {"uv": [1, 2, 15, 3], "texture": "#2"}
			}
		},
		{
			"from": [-1.31689, 2.53143, 6.76563],
			"to": [12.68311, 4.53143, 7.60938],
			"rotation": {"angle": 45, "axis": "z", "origin": [0.98896, 8.26606, 7.74107]},
			"faces": {
				"north": {"uv": [0, 1.5, 14, 3.5], "texture": "#2"},
				"east": {"uv": [8.39063, 3, 9.23438, 5], "texture": "#2"},
				"south": {"uv": [2, 4.5, 16, 6.5], "texture": "#2"},
				"west": {"uv": [6.76563, 3, 7.60938, 5], "texture": "#2"},
				"up": {"uv": [0.5, 2, 14.5, 3], "texture": "#2"},
				"down": {"uv": [1, 2, 15, 3], "texture": "#2"}
			}
		},
		{
			"from": [1.00538, 2.5, 6.75],
			"to": [15.00538, 4.5, 7.75],
			"rotation": {"angle": 0, "axis": "y", "origin": [0.98896, 8.26606, 7.74107]},
			"faces": {
				"north": {"uv": [1, 2, 15, 4], "texture": "#2"},
				"east": {"uv": [8.5, 11, 9.5, 13], "texture": "#2"},
				"south": {"uv": [0.5, 12.5, 14.5, 14.5], "texture": "#2"},
				"west": {"uv": [5.5, 11.5, 6.5, 13.5], "texture": "#2"},
				"up": {"uv": [0.5, 2, 14.5, 3], "texture": "#2"},
				"down": {"uv": [1, 2, 15, 3], "texture": "#2"}
			}
		},
		{
			"from": [8.50538, 0.75, 7.75],
			"to": [10.50538, 15.75, 8.5],
			"rotation": {"angle": 0, "axis": "y", "origin": [0.98896, 8.26606, 7.74107]},
			"faces": {
				"north": {"uv": [5.75, 0.25, 20.75, 2], "rotation": 90, "texture": "#2"},
				"east": {"uv": [7, 0.5, 22, 1], "rotation": 90, "texture": "#2"},
				"south": {"uv": [8.5, 0.25, 23.5, 2.25], "rotation": 90, "texture": "#2"},
				"west": {"uv": [7, 0.5, 22, 1], "rotation": 90, "texture": "#2"},
				"up": {"uv": [8.5, 7.75, 9.25, 9.75], "rotation": 90, "texture": "#2"},
				"down": {"uv": [8.5, 7.5, 9.25, 9.5], "rotation": 90, "texture": "#2"}
			}
		},
		{
			"from": [5.50538, 0.5, 7.75],
			"to": [7.50538, 16.5, 8.5],
			"rotation": {"angle": 0, "axis": "y", "origin": [0.98896, 8.26606, 7.74107]},
			"faces": {
				"north": {"uv": [8.75, 0, 24.25, 1.75], "rotation": 90, "texture": "#2"},
				"east": {"uv": [7, 0.5, 22, 1], "rotation": 90, "texture": "#2"},
				"south": {"uv": [5.5, 0, 21.5, 2], "rotation": 90, "texture": "#2"},
				"west": {"uv": [7, 0.5, 22, 1], "rotation": 90, "texture": "#2"},
				"up": {"uv": [5.5, 7.75, 6.25, 9.75], "rotation": 90, "texture": "#2"},
				"down": {"uv": [5.5, 7.5, 6.25, 9.5], "rotation": 90, "texture": "#2"}
			}
		},
		{
			"from": [2.50538, 0.5, 7.75],
			"to": [4.50538, 15.5, 8.5],
			"rotation": {"angle": 0, "axis": "y", "origin": [0.98896, 8.26606, 7.74107]},
			"faces": {
				"north": {"uv": [11.75, 0.5, 26.75, 2.25], "rotation": 90, "texture": "#2"},
				"east": {"uv": [7, 0.5, 22, 1], "rotation": 90, "texture": "#2"},
				"south": {"uv": [2.5, 0.5, 17.5, 2.5], "rotation": 90, "texture": "#2"},
				"west": {"uv": [7, 0.5, 22, 1], "rotation": 90, "texture": "#2"},
				"up": {"uv": [2.5, 7.75, 3.25, 9.75], "rotation": 90, "texture": "#2"},
				"down": {"uv": [2.5, 7.5, 3.25, 9.5], "rotation": 90, "texture": "#2"}
			}
		}
	],
	"display": {
		"gui": {
			"rotation": [30, 45, 0],
			"scale": [0.63, 0.63, 0.63]
		}
	},
	"groups": [0, 1,
		{
			"name": "group",
			"origin": [10.25, 8.5, 8],
			"children": [2, 3, 4, 5, 6, 7, 8]
		}
	]
}