{
	"credit": "Made with Blockbench",
	"textures": {
		"0": "block/birch_planks",
		"particle": "block/birch_planks"
	},
	"elements": [
		{
			"from": [15, 0, 6.5],
			"to": [16, 16, 9],
			"faces": {
				"north": {"uv": [0, 0, 1, 16], "texture": "#0"},
				"east": {"uv": [7, 0, 9.5, 16], "texture": "#0"},
				"south": {"uv": [15, 0, 16, 16], "texture": "#0"},
				"west": {"uv": [6.5, 0, 9, 16], "texture": "#0"},
				"up": {"uv": [15, 6.5, 16, 9], "texture": "#0"},
				"down": {"uv": [15, 7, 16, 9.5], "texture": "#0"}
			}
		},
		{
			"from": [0, 0, 6.5],
			"to": [1, 16, 9],
			"faces": {
				"north": {"uv": [15, 0, 16, 16], "texture": "#0"},
				"east": {"uv": [7, 0, 9.5, 16], "texture": "#0"},
				"south": {"uv": [0, 0, 1, 16], "texture": "#0"},
				"west": {"uv": [5, 0, 7.5, 16], "texture": "#0"},
				"up": {"uv": [0, 6.5, 1, 9], "texture": "#0"},
				"down": {"uv": [0, 7, 1, 9.5], "texture": "#0"}
			}
		},
		{
			"from": [0.23004, 0.5, 18.50748],
			"to": [0.98004, 16.25, 20.50748],
			"rotation": {"angle": 0, "axis": "y", "origin": [0.98896, 8.26606, 7.74107]},
			"faces": {
				"north": {"uv": [7, 0.5, 7.5, 15.5], "texture": "#0"},
				"east": {"uv": [2.5, 0, 4.25, 15.5], "texture": "#0"},
				"south": {"uv": [7, 0.5, 7.5, 15.5], "texture": "#0"},
				"west": {"uv": [11.75, 0, 13.75, 15.75], "texture": "#0"},
				"up": {"uv": [11.75, 7.75, 13.75, 8.5], "rotation": 90, "texture": "#0"},
				"down": {"uv": [11.75, 7.5, 13.75, 8.25], "rotation": 270, "texture": "#0"}
			}
		},
		{
			"from": [0.98004, 12, 7.74186],
			"to": [1.98004, 14, 21.74186],
			"rotation": {"angle": 0, "axis": "y", "origin": [0.98896, 8.26606, 7.74107]},
			"faces": {
				"north": {"uv": [3.5, 4, 5.5, 5], "rotation": 90, "texture": "#0"},
				"east": {"uv": [1, 0, 3, 14], "rotation": 90, "texture": "#0"},
				"south": {"uv": [9.5, 1.5, 11.5, 2.5], "rotation": 90, "texture": "#0"},
				"west": {"uv": [0.98438, 2, 2.98438, 16], "rotation": 90, "texture": "#0"},
				"up": {"uv": [0.5, 2, 1.5, 16], "rotation": 180, "texture": "#0"},
				"down": {"uv": [1, 2, 2, 16], "texture": "#0"}
			}
		},
		{
			"from": [1.12066, 2.53143, 5.43522],
			"to": [1.96441, 4.53143, 19.43522],
			"rotation": {"angle": -45, "axis": "x", "origin": [0.98896, 8.26606, 7.74107]},
			"faces": {
				"north": {"uv": [6.76563, 3, 8.76563, 3.84375], "rotation": 90, "texture": "#0"},
				"east": {"uv": [0, 3, 2, 17], "rotation": 90, "texture": "#0"},
				"south": {"uv": [8.39063, 3, 10.39063, 3.84375], "rotation": 90, "texture": "#0"},
				"west": {"uv": [3.23438, 3, 5.23438, 17], "rotation": 90, "texture": "#0"},
				"up": {"uv": [0.5, 2, 1.5, 16], "rotation": 180, "texture": "#0"},
				"down": {"uv": [1, 2, 2, 16], "texture": "#0"}
			}
		},
		{
			"from": [0.98004, 2.5, 7.75748],
			"to": [1.98004, 4.5, 21.75748],
			"rotation": {"angle": 0, "axis": "y", "origin": [0.98896, 8.26606, 7.74107]},
			"faces": {
				"north": {"uv": [5.5, 11.5, 7.5, 12.5], "rotation": 90, "texture": "#0"},
				"east": {"uv": [1, 2, 3, 16], "rotation": 90, "texture": "#0"},
				"south": {"uv": [8.5, 11, 10.5, 12], "rotation": 90, "texture": "#0"},
				"west": {"uv": [1, 11.5, 3, 25.5], "rotation": 90, "texture": "#0"},
				"up": {"uv": [0.5, 2, 1.5, 16], "rotation": 180, "texture": "#0"},
				"down": {"uv": [1, 2, 2, 16], "texture": "#0"}
			}
		},
		{
			"from": [0.23004, 0.75, 15.25748],
			"to": [0.98004, 15.75, 17.25748],
			"rotation": {"angle": 0, "axis": "y", "origin": [0.98896, 8.26606, 7.74107]},
			"faces": {
				"north": {"uv": [7, 0.5, 7.5, 15.5], "texture": "#0"},
				"east": {"uv": [5.75, 0.25, 7.5, 15.25], "texture": "#0"},
				"south": {"uv": [7, 0.5, 7.5, 15.5], "texture": "#0"},
				"west": {"uv": [8.5, 0.25, 10.5, 15.25], "texture": "#0"},
				"up": {"uv": [8.5, 7.75, 10.5, 8.5], "rotation": 90, "texture": "#0"},
				"down": {"uv": [8.5, 7.5, 10.5, 8.25], "rotation": 270, "texture": "#0"}
			}
		},
		{
			"from": [0.23004, 0.5, 12.25748],
			"to": [0.98004, 16.5, 14.25748],
			"rotation": {"angle": 0, "axis": "y", "origin": [0.98896, 8.26606, 7.74107]},
			"faces": {
				"north": {"uv": [7, 0.5, 7.5, 15.5], "texture": "#0"},
				"east": {"uv": [8.75, 0, 10.5, 15.5], "texture": "#0"},
				"south": {"uv": [7, 0.5, 7.5, 15.5], "texture": "#0"},
				"west": {"uv": [5.5, 0, 7.5, 16], "texture": "#0"},
				"up": {"uv": [5.5, 7.75, 7.5, 8.5], "rotation": 90, "texture": "#0"},
				"down": {"uv": [5.5, 7.5, 7.5, 8.25], "rotation": 270, "texture": "#0"}
			}
		},
		{
			"from": [0.23004, 0.5, 9.25748],
			"to": [0.98004, 15.5, 11.25748],
			"rotation": {"angle": 0, "axis": "y", "origin": [0.98896, 8.26606, 7.74107]},
			"faces": {
				"north": {"uv": [7, 0.5, 7.5, 15.5], "texture": "#0"},
				"east": {"uv": [11.75, 0.5, 13.5, 15.5], "texture": "#0"},
				"south": {"uv": [7, 0.5, 7.5, 15.5], "texture": "#0"},
				"west": {"uv": [2.5, 0.5, 4.5, 15.5], "texture": "#0"},
				"up": {"uv": [2.5, 7.75, 4.5, 8.5], "rotation": 90, "texture": "#0"},
				"down": {"uv": [2.5, 7.5, 4.5, 8.25], "rotation": 270, "texture": "#0"}
			}
		}
	],
	"groups": [0, 1,
		{
			"name": "group",
			"origin": [10.25, 8.5, 8],
			"children": [2, 3, 4, 5, 6, 7, 8]
		}
	]
}